stepik/__init__.py
stepik/__main__.py
stepik/attempt_cache.py
stepik/course_cache.py
stepik/filemanager.py
stepik/languagemanager.py
stepik/navigation.py
stepik/settings.py
stepik/utils.py
stepik/client/__init__.py
stepik/client/attempt.py
stepik/client/auth.py
stepik/client/consts.py
stepik/client/stepikclient.py
stepik/models/__init__.py
stepik/models/course.py
stepik/models/entity.py
stepik/models/lesson.py
stepik/models/section.py
stepik/models/step.py
stepik/models/unit.py
stepik/models/user.py
stepik_cli-0.4.2.dist-info/METADATA
stepik_cli-0.4.2.dist-info/WHEEL
stepik_cli-0.4.2.dist-info/entry_points.txt
stepik_cli-0.4.2.dist-info/top_level.txt
stepik_cli-0.4.2.dist-info/RECORD
