Metadata-Version: 2.1
Name: stepik-cli
Version: 0.4.2
Summary: A Stepik CLI for students
Home-page: https://github.com/aryarm/stepik-cli
License: UNKNOWN
Platform: UNKNOWN
Classifier: Programming Language :: Python :: 3
Classifier: Operating System :: OS Independent
Requires-Dist: click (>=3.0)
Requires-Dist: requests
Requires-Dist: colorama
Requires-Dist: html2text
